{
    "created_time": "2019-09-09T11:18:56Z",
    "files": [
        {
            "attachment_folder": "",
            "created_time": "2019-09-09T11:19:28Z",
            "id": "762",
            "modified_time": "2024-02-11T15:19:21Z",
            "name": "JVM-基础.md",
            "signature": "85024815357375",
            "tags": [
            ]
        },
        {
            "attachment_folder": "",
            "created_time": "2022-12-16T14:53:28Z",
            "id": "763",
            "modified_time": "2023-03-10T07:21:37Z",
            "name": "JVM-源码分析.md",
            "signature": "177764861544",
            "tags": [
            ]
        },
        {
            "attachment_folder": "",
            "created_time": "2023-05-06T02:37:14Z",
            "id": "780",
            "modified_time": "2024-02-11T09:43:13Z",
            "name": "JVM-性能调优.md",
            "signature": "177776999770",
            "tags": [
            ]
        },
        {
            "attachment_folder": "",
            "created_time": "2023-05-06T02:42:25Z",
            "id": "781",
            "modified_time": "2023-05-06T02:42:57Z",
            "name": "JVM-指令手册.md",
            "signature": "79316844396177",
            "tags": [
            ]
        },
        {
            "attachment_folder": "",
            "created_time": "2023-12-23T03:13:15Z",
            "id": "843",
            "modified_time": "2023-12-23T03:17:21Z",
            "name": "Arthas.md",
            "signature": "177796960331",
            "tags": [
            ]
        },
        {
            "attachment_folder": "",
            "created_time": "2024-02-10T15:05:45Z",
            "id": "857",
            "modified_time": "2024-02-10T15:07:28Z",
            "name": "JVM-GC.md",
            "signature": "177801236681",
            "tags": [
            ]
        },
        {
            "attachment_folder": "",
            "created_time": "2024-02-10T15:16:36Z",
            "id": "858",
            "modified_time": "2024-02-11T10:55:28Z",
            "name": "JVM-类加载.md",
            "signature": "79316868633428",
            "tags": [
            ]
        },
        {
            "attachment_folder": "",
            "created_time": "2024-02-10T15:47:13Z",
            "id": "859",
            "modified_time": "2024-02-11T10:18:30Z",
            "name": "JVM-内存模型.md",
            "signature": "27206030432897",
            "tags": [
            ]
        }
    ],
    "folders": [
    ],
    "id": "542",
    "modified_time": "2022-01-21T11:49:19Z",
    "signature": "88392069717439",
    "version": 3
}
