{
    "attachment_folder": "_v_attachments",
    "config_mgr": "vx.vnotex",
    "created_time": "2020-04-11T23:54:41Z",
    "description": "Code-Note",
    "extra_configs": {
    },
    "history": [
        {
            "last_accessed_time": "2024-02-15T05:04:12Z",
            "line_number": 1914,
            "path": "后端框架/MyBatis/MyBatis-基础.md"
        },
        {
            "last_accessed_time": "2024-02-16T14:00:50Z",
            "line_number": 0,
            "path": "其他/Develop-Environment.md"
        },
        {
            "last_accessed_time": "2024-02-16T14:04:37Z",
            "line_number": 19,
            "path": "分布式微服务/其他/项目搭建模板.md"
        },
        {
            "last_accessed_time": "2024-02-16T14:07:07Z",
            "line_number": 24,
            "path": "分布式微服务/SpringBoot/Spring-Boot-项目搭建模板.md"
        },
        {
            "last_accessed_time": "2024-02-16T14:34:56Z",
            "line_number": 382,
            "path": "Java/Java扩展-代码简洁之道.md"
        },
        {
            "last_accessed_time": "2024-02-18T04:08:52Z",
            "line_number": 1093,
            "path": "后端框架/Spring/Spring-AOP.md"
        },
        {
            "last_accessed_time": "2024-02-18T07:45:06Z",
            "line_number": 19,
            "path": "分布式微服务/SpringCloud/Microservices-Overview.md"
        },
        {
            "last_accessed_time": "2024-02-18T08:46:41Z",
            "line_number": 0,
            "path": "分布式微服务/综合架构/架构-负载均衡.md"
        },
        {
            "last_accessed_time": "2024-02-18T08:48:23Z",
            "line_number": 79,
            "path": "分布式微服务/综合架构/架构-服务容错.md"
        },
        {
            "last_accessed_time": "2024-02-19T01:59:59Z",
            "line_number": 78,
            "path": "分布式微服务/综合架构/架构-缓存.md"
        },
        {
            "last_accessed_time": "2024-02-19T13:59:53Z",
            "line_number": 16,
            "path": "分布式微服务/综合架构/Microservices-Overview.md"
        },
        {
            "last_accessed_time": "2024-02-20T01:16:46Z",
            "line_number": 1,
            "path": "其他/development-software/Postman.md"
        },
        {
            "last_accessed_time": "2024-02-20T01:17:08Z",
            "line_number": 6,
            "path": "DevOps/测试工具/JMeter.md"
        },
        {
            "last_accessed_time": "2024-02-20T01:18:57Z",
            "line_number": 9,
            "path": "DevOps/测试工具/Postman.md"
        },
        {
            "last_accessed_time": "2024-02-20T02:15:43Z",
            "line_number": 7,
            "path": "分布式微服务/分布式文件系统/Distributed-File-System-Overview.md"
        },
        {
            "last_accessed_time": "2024-02-20T03:33:07Z",
            "line_number": 141,
            "path": "分布式微服务/综合架构/架构-基础.md"
        },
        {
            "last_accessed_time": "2024-02-20T03:33:07Z",
            "line_number": 90,
            "path": "分布式微服务/综合架构/分布式系统-基础.md"
        },
        {
            "last_accessed_time": "2024-02-20T04:02:28Z",
            "line_number": 1443,
            "path": "分布式微服务/SpringBoot/Spring-Boot-SQL-Databases.md"
        },
        {
            "last_accessed_time": "2024-02-20T04:02:29Z",
            "line_number": 1382,
            "path": "Java/Java扩展-设计模式.md"
        },
        {
            "last_accessed_time": "2024-02-20T10:34:24Z",
            "line_number": 326,
            "path": "其他/system-software/Common-Software.md"
        },
        {
            "last_accessed_time": "2024-02-21T01:47:14Z",
            "line_number": 670,
            "path": "Database/Redis/Redis-安装部署.md"
        },
        {
            "last_accessed_time": "2024-02-22T23:57:53Z",
            "line_number": 41,
            "path": "分布式微服务/ElasticStack/ElasticStack.md"
        },
        {
            "last_accessed_time": "2024-02-23T00:19:12Z",
            "line_number": 240,
            "path": "并发编程/并发编程-并发容器.md"
        },
        {
            "last_accessed_time": "2024-02-23T02:52:19Z",
            "line_number": 599,
            "path": "并发编程/并发编程-并发工具类.md"
        },
        {
            "last_accessed_time": "2024-02-23T02:52:20Z",
            "line_number": 351,
            "path": "JVM/JVM-性能调优.md"
        },
        {
            "last_accessed_time": "2024-02-23T02:52:21Z",
            "line_number": 1039,
            "path": "分布式微服务/ElasticStack/ElasticSearch.md"
        },
        {
            "last_accessed_time": "2024-02-23T03:51:17Z",
            "line_number": 45,
            "path": "JVM/JVM-基础.md"
        },
        {
            "last_accessed_time": "2024-02-23T03:51:18Z",
            "line_number": 637,
            "path": "JVM/JVM-类加载.md"
        },
        {
            "last_accessed_time": "2024-02-23T03:51:18Z",
            "line_number": 240,
            "path": "JVM/JVM-内存模型.md"
        },
        {
            "last_accessed_time": "2024-02-23T05:16:11Z",
            "line_number": 0,
            "path": "Database/Redis/Redis-操作命令.md"
        },
        {
            "last_accessed_time": "2024-02-23T05:16:13Z",
            "line_number": 403,
            "path": "Database/MySQL/MySQL-锁.md"
        },
        {
            "last_accessed_time": "2024-02-23T05:16:14Z",
            "line_number": 704,
            "path": "Database/MySQL/MySQL-体系架构.md"
        },
        {
            "last_accessed_time": "2024-02-23T05:16:15Z",
            "line_number": 546,
            "path": "Database/MySQL/MySQL-事务.md"
        },
        {
            "last_accessed_time": "2024-02-23T05:18:42Z",
            "line_number": 0,
            "path": "分布式微服务/综合系统架构/分布式系统-基础.md"
        },
        {
            "last_accessed_time": "2024-02-23T05:28:47Z",
            "line_number": 17,
            "path": "分布式微服务/综合系统架构/分布式系统-全局唯一ID.md"
        },
        {
            "last_accessed_time": "2024-02-23T05:28:47Z",
            "line_number": 9,
            "path": "分布式微服务/综合系统架构/分布式系统-分布式锁.md"
        },
        {
            "last_accessed_time": "2024-02-23T05:28:48Z",
            "line_number": 128,
            "path": "分布式微服务/综合系统架构/架构-缓存.md"
        },
        {
            "last_accessed_time": "2024-02-23T05:29:44Z",
            "line_number": 0,
            "path": "分布式微服务/系统架构/分布式系统-基础.md"
        },
        {
            "last_accessed_time": "2024-02-23T05:30:24Z",
            "line_number": 0,
            "path": "分布式微服务/系统架构/分布式系统-分布式锁.md"
        },
        {
            "last_accessed_time": "2024-02-24T02:42:17Z",
            "line_number": 63,
            "path": "其他/system-software/foobar2000.md"
        },
        {
            "last_accessed_time": "2024-02-24T02:42:21Z",
            "line_number": 294,
            "path": "JVM/JVM-GC.md"
        },
        {
            "last_accessed_time": "2024-02-24T02:42:22Z",
            "line_number": 933,
            "path": "Database/Redis/Redis-基础.md"
        },
        {
            "last_accessed_time": "2024-02-24T02:42:22Z",
            "line_number": 250,
            "path": "Database/MySQL/MySQL-运维.md"
        },
        {
            "last_accessed_time": "2024-02-24T11:34:53Z",
            "line_number": 8,
            "path": "分布式微服务/分布式事务/RocketMQ-可靠消息最终一致性事务解决方案.md"
        },
        {
            "last_accessed_time": "2024-02-25T02:03:15Z",
            "line_number": 45,
            "path": "分布式微服务/任务调度/Quartz.md"
        },
        {
            "last_accessed_time": "2024-02-25T02:04:05Z",
            "line_number": 10,
            "path": "分布式微服务/SpringBoot/Spring-Boot-Task-Scheduling.md"
        },
        {
            "last_accessed_time": "2024-02-25T03:03:52Z",
            "line_number": 25,
            "path": "分布式微服务/任务调度/XXL-JOB.md"
        },
        {
            "last_accessed_time": "2024-02-25T03:23:14Z",
            "line_number": 0,
            "path": "后端框架/Authorization-Certification/Spring-Security.md"
        },
        {
            "last_accessed_time": "2024-02-25T03:23:14Z",
            "line_number": 14,
            "path": "后端框架/Authorization-Certification/Authorization-Overview.md"
        },
        {
            "last_accessed_time": "2024-02-25T03:34:45Z",
            "line_number": 2,
            "path": "分布式微服务/任务调度/ElasticJob.md"
        },
        {
            "last_accessed_time": "2024-02-25T03:34:45Z",
            "line_number": 248,
            "path": "分布式微服务/任务调度/Task-Scheduling.md"
        },
        {
            "last_accessed_time": "2024-02-25T03:56:17Z",
            "line_number": 123,
            "path": "分布式微服务/系统架构/架构-分布式锁.md"
        },
        {
            "last_accessed_time": "2024-02-25T03:56:17Z",
            "line_number": 8,
            "path": "Database/Redis/Redis-场景应用设计.md"
        },
        {
            "last_accessed_time": "2024-02-25T03:56:17Z",
            "line_number": 71,
            "path": "分布式微服务/服务注册中心/Zookeeper-应用场景.md"
        },
        {
            "last_accessed_time": "2024-02-25T03:56:17Z",
            "line_number": 68,
            "path": "分布式微服务/系统架构/架构-全局唯一ID.md"
        },
        {
            "last_accessed_time": "2024-02-25T03:56:17Z",
            "line_number": 137,
            "path": "分布式微服务/分布式事务/分布式事务基础理论.md"
        },
        {
            "last_accessed_time": "2024-02-25T03:56:17Z",
            "line_number": 994,
            "path": "分布式微服务/消息中件间/RocketMQ.md"
        },
        {
            "last_accessed_time": "2024-02-26T01:23:01Z",
            "line_number": 2135,
            "path": "Java/Java基础-语法.md"
        },
        {
            "last_accessed_time": "2024-02-26T03:22:39Z",
            "line_number": 4531,
            "path": "Java/Java基础-Java8新特性.md"
        },
        {
            "last_accessed_time": "2024-02-26T03:22:40Z",
            "line_number": 14,
            "path": "Java/Java基础-注解.md"
        },
        {
            "last_accessed_time": "2024-02-26T04:44:28Z",
            "line_number": 43,
            "path": "Java/Java扩展-数据结构.md"
        },
        {
            "last_accessed_time": "2024-02-26T04:44:28Z",
            "line_number": 1383,
            "path": "Java/Java扩展-算法.md"
        },
        {
            "last_accessed_time": "2024-02-26T04:44:30Z",
            "line_number": 1700,
            "path": "Java/Java基础-反射.md"
        },
        {
            "last_accessed_time": "2024-02-26T04:44:30Z",
            "line_number": 895,
            "path": "Java/Java基础-集合.md"
        },
        {
            "last_accessed_time": "2024-02-26T04:44:30Z",
            "line_number": 1100,
            "path": "Java/Java扩展-集合类源码分析.md"
        },
        {
            "last_accessed_time": "2024-02-26T06:27:31Z",
            "line_number": 5,
            "path": "后端框架/工具框架/Netty.md"
        },
        {
            "last_accessed_time": "2024-02-26T08:06:14Z",
            "line_number": 14,
            "path": "后端框架/工具框架/iTextPdf.md"
        },
        {
            "last_accessed_time": "2024-02-26T08:46:34Z",
            "line_number": 28,
            "path": "其他/development-software/Common-Development.md"
        },
        {
            "last_accessed_time": "2024-02-26T08:49:47Z",
            "line_number": 0,
            "path": "其他/software/Web-Browser.md"
        },
        {
            "last_accessed_time": "2024-02-26T09:01:41Z",
            "line_number": 0,
            "path": "其他/software/Common-Development.md"
        },
        {
            "last_accessed_time": "2024-02-26T09:16:36Z",
            "line_number": 3,
            "path": "其他/OS.md"
        },
        {
            "last_accessed_time": "2024-02-26T09:21:26Z",
            "line_number": 9,
            "path": "其他/编程资源分享.md"
        },
        {
            "last_accessed_time": "2024-02-26T09:21:31Z",
            "line_number": 1609,
            "path": "并发编程/并发编程-多线程.md"
        },
        {
            "last_accessed_time": "2024-02-26T09:21:32Z",
            "line_number": 1137,
            "path": "并发编程/并发编程-线程安全与锁.md"
        },
        {
            "last_accessed_time": "2024-02-26T09:21:32Z",
            "line_number": 207,
            "path": "并发编程/并发编程-AQS.md"
        },
        {
            "last_accessed_time": "2024-02-26T09:21:32Z",
            "line_number": 933,
            "path": "分布式微服务/系统架构/架构-基础.md"
        },
        {
            "last_accessed_time": "2024-02-26T09:21:32Z",
            "line_number": 24,
            "path": "其他/编程开发相关.md"
        },
        {
            "last_accessed_time": "2024-02-26T09:23:21Z",
            "line_number": 0,
            "path": "Java/Java基础-对象与类.md"
        },
        {
            "last_accessed_time": "2024-02-26T09:29:59Z",
            "line_number": 372,
            "path": "后端框架/工具框架/Apache-Commons.md"
        },
        {
            "last_accessed_time": "2024-02-26T09:30:10Z",
            "line_number": 1477,
            "path": "Java/Java基础-数据库编程.md"
        },
        {
            "last_accessed_time": "2024-02-26T23:23:03Z",
            "line_number": 24,
            "path": "DevOps/测试工具/Testing-Overview.md"
        },
        {
            "last_accessed_time": "2024-02-26T23:23:09Z",
            "line_number": 0,
            "path": "DevOps/测试工具/JUnit4.md"
        },
        {
            "last_accessed_time": "2024-02-27T01:43:18Z",
            "line_number": 813,
            "path": "项目资料/万信金融/03-用户登陆与认证授权.md"
        },
        {
            "last_accessed_time": "2024-02-27T01:44:24Z",
            "line_number": 360,
            "path": "项目资料/万信金融/01-项目介绍与开发环境搭建.md"
        },
        {
            "last_accessed_time": "2024-02-27T02:05:01Z",
            "line_number": 10,
            "path": "项目资料/万信金融/04-分布式事务解决方案-Hmily.md"
        },
        {
            "last_accessed_time": "2024-02-27T04:17:21Z",
            "line_number": 14,
            "path": "分布式微服务/SpringBoot/Spring-Boot-Testing.md"
        },
        {
            "last_accessed_time": "2024-02-27T04:17:24Z",
            "line_number": 581,
            "path": "分布式微服务/SpringBoot/Spring-Boot-注解汇总.md"
        },
        {
            "last_accessed_time": "2024-02-27T04:51:20Z",
            "line_number": 2524,
            "path": "分布式微服务/SpringBoot/Spring-Boot-基础篇.md"
        },
        {
            "last_accessed_time": "2024-02-27T05:14:03Z",
            "line_number": 206,
            "path": "分布式微服务/SpringCloud/Spring-Cloud-Netflix-Eureka.md"
        },
        {
            "last_accessed_time": "2024-02-27T06:16:54Z",
            "line_number": 173,
            "path": "分布式微服务/SpringCloud/Spring-Cloud-Netflix-Ribbon.md"
        },
        {
            "last_accessed_time": "2024-02-27T06:16:55Z",
            "line_number": 330,
            "path": "分布式微服务/SpringCloud/Spring-Cloud-OpenFeign.md"
        },
        {
            "last_accessed_time": "2024-02-27T06:28:29Z",
            "line_number": 1388,
            "path": "分布式微服务/SpringCloud/Spring-Cloud-Alibaba-Sentinel.md"
        },
        {
            "last_accessed_time": "2024-02-27T14:10:39Z",
            "line_number": 430,
            "path": "其他/software/Common-Software.md"
        },
        {
            "last_accessed_time": "2024-02-27T14:49:04Z",
            "line_number": 582,
            "path": "并发编程/并发编程-线程池.md"
        },
        {
            "last_accessed_time": "2024-02-27T14:49:05Z",
            "line_number": 736,
            "path": "Java/Java基础-异常.md"
        },
        {
            "last_accessed_time": "2024-02-27T14:49:05Z",
            "line_number": 3717,
            "path": "并发编程/并发编程-原理篇.md"
        },
        {
            "last_accessed_time": "2024-02-27T14:49:06Z",
            "line_number": 0,
            "path": "项目资料/万信金融/02-前端环境搭建与短信校验注册功能.md"
        },
        {
            "last_accessed_time": "2024-02-27T14:49:07Z",
            "line_number": 808,
            "path": "分布式微服务/SpringBoot/Spring-Boot-部署运维篇.md"
        },
        {
            "last_accessed_time": "2024-02-27T14:49:07Z",
            "line_number": 275,
            "path": "分布式微服务/SpringCloud/Spring-Cloud-Alibaba-Nacos.md"
        },
        {
            "last_accessed_time": "2024-02-27T14:49:08Z",
            "line_number": 124,
            "path": "分布式微服务/Authorization-Certification/Authorization-Overview.md"
        }
    ],
    "image_folder": "images",
    "name": "code-learning-note",
    "tag_graph": "",
    "version": 3,
    "version_controller": "dummy.vnotex"
}
